pyamis/__init__.py
pyamis/comm.py
pyamis/base/__init__.py
pyamis/base/api.py
pyamis/base/base.py
pyamis/components/__init__.py
pyamis/components/action.py
pyamis/components/app_page.py
pyamis/components/chart.py
pyamis/components/crud.py
pyamis/components/form.py
pyamis/components/page.py
pyamis/components/service.py
pyamis/components/form/__init__.py
pyamis/components/form/form.py
pyamis/components/form/formdate.py
pyamis/components/form/formdaterange.py
pyamis/components/form/formdatetime.py
pyamis/components/form/formdatetimerange.py
pyamis/components/form/formitem.py
pyamis/components/form/formlocation.py
pyamis/components/form/formmonth.py
pyamis/components/form/formmonthrange.py
pyamis/components/form/formtext.py
pyamis/components/form/formtextarea.py
py_amis-0.0.1.dist-info/LICENSE
py_amis-0.0.1.dist-info/METADATA
py_amis-0.0.1.dist-info/WHEEL
py_amis-0.0.1.dist-info/top_level.txt
py_amis-0.0.1.dist-info/RECORD
