Metadata-Version: 2.1
Name: py-amis
Version: 0.0.1
Summary: python gen amis json options
Home-page: https://github.com/1178615156/pyamis
Author: yujieshui
Author-email: a1178615156@gmail.com
License: UNKNOWN
Platform: UNKNOWN
Classifier: Programming Language :: Python :: 3
Classifier: License :: OSI Approved :: MIT License
Classifier: Operating System :: OS Independent
